ana_sales/sales.py
ana_sales/settings.py
ana_sales-0.0.1.dist-info/METADATA
ana_sales-0.0.1.dist-info/WHEEL
ana_sales-0.0.1.dist-info/RECORD
